[
  {
    "id": "c49206c9-267d-4731-bc6c-fe5f2c2a7e1d",
    "name": "some string",
    "email": "address@email.com",
    "phoneNumber": 123,
    "content": "User's message goes here"
  },
  {
    "id": "1fabe4de-3e13-4d8b-9912-5c7ac793da5a",
    "name": "flo",
    "phoneNumber": "asd",
    "email": "flo@gmail.com",
    "content": "asdfgh"
  },
  {
    "id": "581898b5-de40-496c-9ca1-ff5a741c07e4",
    "name": "test",
    "phoneNumber": "111",
    "email": "test@test.com",
    "content": "test"
  },
  {
    "id": "005290dd-20ff-40ea-9c0a-053cbcacf9c3",
    "name": "some string",
    "email": "address@email.com",
    "phoneNumber": "2343331234",
    "content": "User's message goes here"
  },
  {
    "id": "94004174-4edd-4898-b9b5-8be160844275",
    "name": "some string",
    "email": "address@email.com",
    "phoneNumber": "2343331234",
    "content": "User's message goes here"
  }
]